make_bitvector/__init__.py
make_bitvector/alignedRead.py
make_bitvector/helper.py
make_bitvector/hiseq_to_bitvector.py
make_bitvector/make_bitvector.py
make_bitvector/miseq_to_bitvector.py
make_bitvector-2.0.6.dist-info/DESCRIPTION.rst
make_bitvector-2.0.6.dist-info/METADATA
make_bitvector-2.0.6.dist-info/RECORD
make_bitvector-2.0.6.dist-info/WHEEL
make_bitvector-2.0.6.dist-info/entry_points.txt
make_bitvector-2.0.6.dist-info/metadata.json
make_bitvector-2.0.6.dist-info/top_level.txt
