Metadata-Version: 2.0
Name: make-bitvector
Version: 2.0.6
Summary: Create bitvectors for DMS seq data
Home-page: https://gitlab.com/Rouskin-Lab/bitvector
Author: Rouskin-Lab
Author-email: srouskin@wi.mit.edu
License: MIT
Platform: UNKNOWN
Classifier: Development Status :: 3 - Alpha
Classifier: Intended Audience :: Developers
Classifier: License :: OSI Approved :: MIT License
Classifier: Programming Language :: Python :: 2.7
Requires-Dist: multiprocessing
Requires-Dist: numpy
Requires-Dist: pandas
Requires-Dist: pysam
